pybase16384/__init__.py
pybase16384/_core.abi3.so
pybase16384/build.py
pybase16384_cffi-0.1.0.dist-info/METADATA
pybase16384_cffi-0.1.0.dist-info/WHEEL
pybase16384_cffi-0.1.0.dist-info/top_level.txt
pybase16384_cffi-0.1.0.dist-info/RECORD
